pinionai/__init__.py
pinionai/_crypto.py
pinionai/chatservice_pb2.py
pinionai/chatservice_pb2.pyi
pinionai/chatservice_pb2_grpc.py
pinionai/client.py
pinionai/exceptions.py
pinionai/protos/__init__.py
pinionai/protos/chatservice.proto
pinionai-0.2.4.dist-info/licenses/LICENSE
pinionai-0.2.4.dist-info/METADATA
pinionai-0.2.4.dist-info/WHEEL
pinionai-0.2.4.dist-info/entry_points.txt
pinionai-0.2.4.dist-info/top_level.txt
pinionai-0.2.4.dist-info/RECORD
