Metadata-Version: 2.4
Name: pinionai
Version: 0.2.4
Summary: The official Python client library for the PinionAI platform.
Author-email: Alan Johnson <alan@pinionai.com>, PinionAI <info@pinionai.com>
License-Expression: MIT
Project-URL: Documentation, https://docs.pinionai.com/
Project-URL: Homepage, https://www.pinionai.com/
Project-URL: Issues, https://www.pinionai.com/contact
Project-URL: GitHub, https://github.com/pinionai/pinionai-streamlit-agent
Classifier: Programming Language :: Python :: 3
Classifier: Programming Language :: Python :: 3.10
Classifier: Programming Language :: Python :: 3.11
Classifier: Programming Language :: Python :: 3.12
Classifier: Programming Language :: Python :: 3.13
Classifier: Operating System :: OS Independent
Classifier: Intended Audience :: Developers
Classifier: Topic :: Software Development :: Libraries :: Python Modules
Classifier: Topic :: Scientific/Engineering :: Artificial Intelligence
Requires-Python: >=3.10
License-File: LICENSE
Requires-Dist: grpcio
Requires-Dist: protobuf
Requires-Dist: httpx[http2]
Requires-Dist: python-Levenshtein
Requires-Dist: Markdown
Requires-Dist: pandas
Requires-Dist: xmltodict
Requires-Dist: google-genai>=1.56.0
Requires-Dist: fastmcp
Requires-Dist: jsonpath-ng
Requires-Dist: websockets
Requires-Dist: cryptography
Provides-Extra: dev
Requires-Dist: build; extra == "dev"
Requires-Dist: twine; extra == "dev"
Requires-Dist: ruff; extra == "dev"
Requires-Dist: grpcio-tools; extra == "dev"
Provides-Extra: gcp
Requires-Dist: google-cloud-storage>=3.0.0; extra == "gcp"
Provides-Extra: aws
Requires-Dist: boto3; extra == "aws"
Provides-Extra: openai
Requires-Dist: openai; extra == "openai"
Provides-Extra: anthropic
Requires-Dist: anthropic; extra == "anthropic"
Provides-Extra: javascript
Requires-Dist: mini-racer; extra == "javascript"
Provides-Extra: sendgrid
Requires-Dist: sendgrid; extra == "sendgrid"
Provides-Extra: twilio
Requires-Dist: twilio; extra == "twilio"
Provides-Extra: all
Requires-Dist: pinionai[anthropic,aws,gcp,javascript,openai,sendgrid,twilio]; extra == "all"
Dynamic: license-file
